{
    "name": "root",
    "metadata": {
        "timer_format_version": "0.1.0",
        "start_time_seconds": "1705310927",
        "python_version": "3.10.12 (main, Nov 20 2023, 15:14:05) [GCC 11.4.0]",
        "command_line_arguments": "/home/kamyk/.local/bin/mlagents-learn config/NavigateToSpot.yaml --run-id=NavigateToSpotRealSpeed --resume",
        "mlagents_version": "1.0.0",
        "mlagents_envs_version": "1.0.0",
        "communication_protocol_version": "1.5.0",
        "pytorch_version": "2.1.1+cu121",
        "numpy_version": "1.21.2",
        "end_time_seconds": "1705310997"
    },
    "total": 70.2249623140001,
    "count": 1,
    "self": 0.031810600999961025,
    "children": {
        "run_training.setup": {
            "total": 0.059963269000036235,
            "count": 1,
            "self": 0.059963269000036235
        },
        "TrainerController.start_learning": {
            "total": 70.1331884440001,
            "count": 1,
            "self": 0.0064560550001715455,
            "children": {
                "TrainerController._reset_env": {
                    "total": 70.12590756700001,
                    "count": 1,
                    "self": 70.12590756700001
                },
                "TrainerController._save_models": {
                    "total": 0.0008248219999131834,
                    "count": 1,
                    "self": 0.0008248219999131834
                }
            }
        }
    }
}